{
  "id": "pkg:maven/com.google.cloud/google-cloud-profiler",
  "description": "is a statistical, low-overhead profiler that continuously gathers CPU usage and memory-allocation information from your production applications. It attributes that information to the application's source code, helping you identify the parts of the application consuming the most resources, and otherwise illuminating the performance characteristics of the code.",
  "group_id": "com.google.cloud",
  "artifact_id": "google-cloud-profiler",
  "version_latest": "2.70.0",
  "ts_publish": 1753909539000,
  "ts_update": 1753914464398,
  "count_dep": 80,
  "count_ref": 0,
  "licenses": [
    "Apache-2.0"
  ],
  "categories": [
    "Cloud Computing"
  ],
  "dsv": 1
}