{
	"id":"pkg:maven/io.github.growthbook/NetworkDispatcherKtor-jvm",
	"description":"Network Dispatcher based on Ktor",
	"group_id":"io.github.growthbook",
	"artifact_id":"NetworkDispatcherKtor-jvm",
	"version_latest":"1.0.6",
	"ts_publish":1754419568000,
	"ts_update":1754463239897,
	"count_dep":22,
	"count_ref":0,
	"licenses":[
		"MIT"
	],
	"dsv":1,
	"url_project":"https://github.com/growthbook/growthbook-kotlin",
	"url_oss_index":"https://ossindex.sonatype.org/component/pkg:maven/io.github.growthbook/NetworkDispatcherKtor-jvm@1.0.6",
	"url_issue_management":"https://github.com/growthbook/growthbook-kotlin/issues",
	"contributors":[
		"Bohdan Kim"
	],
	"url_scm":"https://github.com/growthbook/growthbook-kotlin"
}