{
  "id": "pkg:maven/ru.astrainteractive.gradleplugin.detekt.compose/ru.astrainteractive.gradleplugin.detekt.compose.gradle.plugin",
  "description": "GradlePlugin for my kotlin projects",
  "group_id": "ru.astrainteractive.gradleplugin.detekt.compose",
  "artifact_id": "ru.astrainteractive.gradleplugin.detekt.compose.gradle.plugin",
  "version_latest": "1.11.0",
  "ts_publish": 1754129228000,
  "ts_update": 1754129748981,
  "count_dep": 1,
  "count_ref": 0,
  "licenses": [
    "Apache-2.0"
  ],
  "categories": null,
  "dsv": 1
}