{
	"id":"pkg:maven/org.hansken.plugin.extraction/sdk-java",
	"description":"Hansken Extraction Plugin SDK provides a full set of APIs, runtimes, and test framework to develop\n        extraction plugins for the Hansken Digital Forensics as a Service platform.",
	"group_id":"org.hansken.plugin.extraction",
	"artifact_id":"sdk-java",
	"version_latest":"0.9.9",
	"ts_publish":1754477914000,
	"dt_publish":"2025-08-06 18:58:34.000",
	"ts_update":1754482087835,
	"dt_update":"2025-08-06 20:10:03.498",
	"count_dep":11,
	"count_ref":0,
	"licenses":[
		"The Apache Software License, Version 2.0"
	],
	"dsv":1,
	"url_project":"https://netherlandsforensicinstitute.github.io/hansken-extraction-plugin-sdk-documentation/sdk-java",
	"url_oss_index":"https://ossindex.sonatype.org/component/pkg:maven/org.hansken.plugin.extraction/sdk-java@0.9.9",
	"contributors":[
		"Hansken development team"
	],
	"url_scm":"https://github.com/NetherlandsForensicInstitute/hansken-extraction-plugin-sdk-documentation/sdk-java"
}