{
  "id": "pkg:maven/org.finos.legend.engine/legend-engine-pure-functions-json-pure",
  "description": "Parent POM for FINOS hosted project that deliver release, publishing automation and more",
  "group_id": "org.finos.legend.engine",
  "artifact_id": "legend-engine-pure-functions-json-pure",
  "version_latest": "4.95.0",
  "ts_publish": 1754035364000,
  "ts_update": 1754036824292,
  "count_dep": 18,
  "count_ref": 50,
  "licenses": [
    "Apache License, Version 2.0"
  ],
  "categories": [
    "Uncategorized"
  ],
  "dsv": 1
}