{
  "group_id": "de.knightsoft-net",
  "artifact_id": "gwt-bean-validators-rest-resolver",
  "latest_version": "2.4.6",
  "description": "The GWT Bean Validators REST resolver is used to reduce client side code.\n\t\tInstead of compiling phone number and bank account data into java-script code, it is taken from server by REST get call.",
  "id": "pkg:maven/de.knightsoft-net/gwt-bean-validators-rest-resolver",
  "ts": 1753360898000,
  "dependency_count": 4,
  "ref_count": 60,
  "categories": [
    "MULTI-PROJECT"
  ],
  "licenses": [
    "Apache License, Version 2.0"
  ],
  "last_updated": 1753361815241
}