{
  "group_id": "org.springframework.boot",
  "artifact_id": "spring-boot-starter-webclient",
  "latest_version": "4.0.0-M1",
  "description": "Starter using Spring's reactive HTTP clients (WebClient and HTTP Service Clients)",
  "id": "pkg:maven/org.springframework.boot/spring-boot-starter-webclient",
  "ts": 1753374723000,
  "dependency_count": 0,
  "ref_count": 37,
  "categories": [
    "Dependency Injection and Aspect-Oriented"
  ],
  "licenses": [
    "Apache License, Version 2.0"
  ],
  "last_updated": 1753375371803
}