{
  "id": "pkg:maven/io.quarkiverse.kafkastreamsprocessor/quarkus-kafka-streams-processor-deployment",
  "description": "Parent POM for Quarkiverse projects that includes the default release and artifact publishing related\n    configuration",
  "group_id": "io.quarkiverse.kafkastreamsprocessor",
  "artifact_id": "quarkus-kafka-streams-processor-deployment",
  "version_latest": "5.0.1",
  "ts_publish": 1754497596000,
  "dt_publish": "2025-08-07 00:26:36.000",
  "ts_update": 1754498124362,
  "dt_update": "2025-08-07 00:35:24.362",
  "count_dep": 330,
  "count_ref": 0,
  "licenses": [
    "Apache License, Version 2.0"
  ],
  "categories": null,
  "dsv": 1
}