{
  "group_id": "com.paydock.core",
  "artifact_id": "network-android",
  "latest_version": "0.0.1",
  "description": "A versatile and robust networking module for Kotlin Multiplatform (KMP) projects, utilizing Ktor with platform-specific engines. Supports dynamic HTTP client engine creation, including success and failure mock engines, interceptor-based OkHttp for Android, and SSL pinning configurations. This library ensures seamless integration and consistent networking functionality across Android and iOS, making it ideal for both production and testing environments.",
  "id": "pkg:maven/com.paydock.core/network-android",
  "ts": 1753277790000,
  "dependency_count": 0,
  "ref_count": 13,
  "categories": null,
  "licenses": [
    "The Apache License, Version 2.0"
  ],
  "last_updated": 1753278421403
}