{
	"id":"pkg:maven/pro.cyberyon/mojet",
	"description":"An extended spring-batch bean wrapper",
	"group_id":"pro.cyberyon",
	"artifact_id":"mojet",
	"version_latest":"1.3.0",
	"ts_publish":1754424543000,
	"ts_update":1754463239995,
	"count_dep":20,
	"count_ref":0,
	"licenses":[
		"The Apache License, Version 2.0"
	],
	"dsv":1,
	"url_project":"https://github.com/gchauvet/mojet",
	"url_oss_index":"https://ossindex.sonatype.org/component/pkg:maven/pro.cyberyon/mojet@1.3.0",
	"url_scm":"https://github.com/gchauvet/mojet"
}