{
  "id": "pkg:maven/com.arpnetworking.metrics/metrics-aggregator-daemon",
  "description": "Aggregates samples published by metrics client libraries and writes to destinations.",
  "group_id": "com.arpnetworking.metrics",
  "artifact_id": "metrics-aggregator-daemon",
  "version_latest": "1.22.14",
  "ts_publish": 1754109765000,
  "ts_update": 1754109975735,
  "count_dep": 123,
  "count_ref": 0,
  "licenses": [
    "Apache License, Version 2.0"
  ],
  "categories": [
    "Analytics"
  ],
  "dsv": 1
}