{
	"id":"pkg:maven/org.scalamock/scalamock-zio_2.12",
	"description":"scalamock-zio",
	"group_id":"org.scalamock",
	"artifact_id":"scalamock-zio_2.12",
	"version_latest":"7.4.1",
	"ts_publish":1754476819000,
	"dt_publish":"2025-08-06 18:40:19.000",
	"ts_update":1754482090300,
	"dt_update":"2025-08-06 20:10:03.506",
	"count_dep":11,
	"count_ref":0,
	"licenses":[
		"MIT"
	],
	"categories":[
		"Test and Quality Management",
		"Mocking Utilities"
	],
	"dsv":1,
	"url_project":"http://scalamock.org/",
	"url_oss_index":"https://ossindex.sonatype.org/component/pkg:maven/org.scalamock/scalamock-zio_2.12@7.4.1",
	"contributors":[
		"Philipp Meyerhoefer",
		"Paul Butcher",
		"Georgii Kovalev"
	],
	"url_scm":"https://github.com/scalamock/scalamock"
}