{
  "id": "pkg:maven/com.phactum.lpm/lpm-adapter-common",
  "description": "API for ingesting signals for process monitoring.",
  "group_id": "com.phactum.lpm",
  "artifact_id": "lpm-adapter-common",
  "version_latest": "0.9.9",
  "ts_publish": 1754483111000,
  "dt_publish": "2025-08-06 20:25:11.000",
  "ts_update": 1754484430304,
  "dt_update": "2025-08-06 20:47:10.304",
  "count_dep": 3,
  "count_ref": 2,
  "licenses": [
    "The Apache License, Version 2.0"
  ],
  "categories": null,
  "dsv": 1
}