{
  "group_id": "uk.gov.justice.service.hmpps",
  "artifact_id": "hmpps-sqs-spring-boot-autoconfigure",
  "latest_version": "5.4.10",
  "description": "A Spring Boot Autoconfigure library providing utilities for using amazon-sqs-java-messaging-lib",
  "id": "pkg:maven/uk.gov.justice.service.hmpps/hmpps-sqs-spring-boot-autoconfigure",
  "ts": 1753429666000,
  "dependency_count": 1,
  "ref_count": 57,
  "categories": [
    "Uncategorized"
  ],
  "licenses": [
    "MIT"
  ],
  "last_updated": 1753430113917
}