{
  "id": "pkg:maven/com.bazaarvoice.emodb/emodb-databus-api",
  "description": "Sonatype helps open source projects to set up Maven repositories on https://oss.sonatype.org/",
  "group_id": "com.bazaarvoice.emodb",
  "artifact_id": "emodb-databus-api",
  "version_latest": "6.5.238",
  "ts_publish": 1753790743000,
  "ts_update": 1753795630800,
  "count_dep": 17,
  "count_ref": 9,
  "licenses": [
    "Apache License, Version 2.0"
  ],
  "categories": [
    "Data Management",
    "Database"
  ],
  "dsv": 1
}